MANIFEST.in
README.rst
setup.py
docs/HISTORY.txt
docs/LICENSE.GPL
docs/LICENSE.txt
izug/__init__.py
izug.refegovservice.egg-info/PKG-INFO
izug.refegovservice.egg-info/SOURCES.txt
izug.refegovservice.egg-info/dependency_links.txt
izug.refegovservice.egg-info/entry_points.txt
izug.refegovservice.egg-info/namespace_packages.txt
izug.refegovservice.egg-info/not-zip-safe
izug.refegovservice.egg-info/requires.txt
izug.refegovservice.egg-info/top_level.txt
izug/refegovservice/__init__.py
izug/refegovservice/config.py
izug/refegovservice/configure.zcml
izug/refegovservice/egovleistung.py
izug/refegovservice/egovleistung_view.py
izug/refegovservice/interfaces.py
izug/refegovservice/lawgiver.zcml
izug/refegovservice/permissions.zcml
izug/refegovservice/refegovservice.py
izug/refegovservice/resources.zcml
izug/refegovservice/testing.py
izug/refegovservice/Extensions/__init__.py
izug/refegovservice/Extensions/install.py
izug/refegovservice/content/__init__.py
izug/refegovservice/content/e_gov_service.py
izug/refegovservice/content/ref_e_gov_service.py
izug/refegovservice/locales/izug.refegovservice.pot
izug/refegovservice/locales/plone.pot
izug/refegovservice/locales/de/LC_MESSAGES/izug.refegovservice.po
izug/refegovservice/locales/de/LC_MESSAGES/plone.po
izug/refegovservice/locales/en/LC_MESSAGES/izug.refegovservice.po
izug/refegovservice/locales/en/LC_MESSAGES/plone.po
izug/refegovservice/profiles/default/jsregistry.xml
izug/refegovservice/profiles/default/metadata.xml
izug/refegovservice/profiles/default/rolemap.xml
izug/refegovservice/profiles/default/types.xml
izug/refegovservice/profiles/default/types/izug.refegovservice.egovservice.xml
izug/refegovservice/profiles/default/types/izug.refegovservice.refegovservice.xml
izug/refegovservice/profiles/default_plone5/metadata.xml
izug/refegovservice/profiles/default_plone5/registry.xml
izug/refegovservice/profiles/default_plone5/rolemap.xml
izug/refegovservice/profiles/default_plone5/types.xml
izug/refegovservice/profiles/default_plone5/types/izug.refegovservice.egovservice.xml
izug/refegovservice/profiles/default_plone5/types/izug.refegovservice.refegovservice.xml
izug/refegovservice/profiles/uninstall/jsregistry.xml
izug/refegovservice/profiles/uninstall/rolemap.xml
izug/refegovservice/profiles/uninstall/types.xml
izug/refegovservice/profiles/uninstall_plone5/registry.xml
