Metadata-Version: 2.1
Name: izug.refegovservice
Version: 3.1.2
Summary: RefEgovService for izug/zug.ch
Home-page: https://nourl
Author: 4teamwork GmbH
Author-email: mailto:info@4teamwork.ch
License: GPL2
Keywords: izug refegovservice
Platform: UNKNOWN
Classifier: Framework :: Plone
Classifier: Framework :: Plone :: 4.3
Classifier: Framework :: Plone :: 5.1
Classifier: Programming Language :: Python
Classifier: Topic :: Software Development :: Libraries :: Python Modules
Provides-Extra: tests
